bulletgym/__init__.py
bulletgym/envs/__init__.py
bulletgym/envs/pandaEnv.py
bullet_gym-0.0.1.dist-info/METADATA
bullet_gym-0.0.1.dist-info/WHEEL
bullet_gym-0.0.1.dist-info/top_level.txt
bullet_gym-0.0.1.dist-info/RECORD
