Metadata-Version: 1.0
Name: bullet-gym
Version: 0.0.1
Summary: A OpenAI Gym Env for pandas
Home-page: UNKNOWN
Author: UNKNOWN
Author-email: UNKNOWN
License: UNKNOWN
Platform: UNKNOWN
